gitcollect/__init__.py
gitcollect/main.py
gitcollect-1.8.0.dist-info/LICENSE
gitcollect-1.8.0.dist-info/METADATA
gitcollect-1.8.0.dist-info/WHEEL
gitcollect-1.8.0.dist-info/top_level.txt
gitcollect-1.8.0.dist-info/RECORD
