Metadata-Version: 2.1
Name: gitcollect
Version: 1.8.0
Summary: it gets github info
Home-page: https://github.com/LogSkele/gitcollect
Author: iop3
Author-email: keystove@gmail.com
Project-URL: Bug Tracker, https://github.com/LogSkele/gitcollect/issues
Classifier: Programming Language :: Python :: 3
Classifier: License :: OSI Approved :: MIT License
Classifier: Operating System :: OS Independent
Requires-Python: >=3.6
License-File: LICENSE
